pyats/utils/__init__.py
pyats/utils/__legacy_imports__.cpython-313-aarch64-linux-gnu.so
pyats/utils/ansi.cpython-313-aarch64-linux-gnu.so
pyats/utils/cli_parse_helpers.cpython-313-aarch64-linux-gnu.so
pyats/utils/commands.cpython-313-aarch64-linux-gnu.so
pyats/utils/dicts.cpython-313-aarch64-linux-gnu.so
pyats/utils/email.cpython-313-aarch64-linux-gnu.so
pyats/utils/exceptions.cpython-313-aarch64-linux-gnu.so
pyats/utils/fileutils.cpython-313-aarch64-linux-gnu.so
pyats/utils/locations.cpython-313-aarch64-linux-gnu.so
pyats/utils/objects.cpython-313-aarch64-linux-gnu.so
pyats/utils/parser.cpython-313-aarch64-linux-gnu.so
pyats/utils/schemaengine.cpython-313-aarch64-linux-gnu.so
pyats/utils/secret_strings.cpython-313-aarch64-linux-gnu.so
pyats/utils/sig_handlers.cpython-313-aarch64-linux-gnu.so
pyats/utils/strings.cpython-313-aarch64-linux-gnu.so
pyats/utils/utils.cpython-313-aarch64-linux-gnu.so
pyats/utils/import_utils/__init__.py
pyats/utils/import_utils/flex.cpython-313-aarch64-linux-gnu.so
pyats/utils/import_utils/legacy.cpython-313-aarch64-linux-gnu.so
pyats/utils/import_utils/misc.cpython-313-aarch64-linux-gnu.so
pyats/utils/yaml/__init__.py
pyats/utils/yaml/dumper.cpython-313-aarch64-linux-gnu.so
pyats/utils/yaml/exceptions.cpython-313-aarch64-linux-gnu.so
pyats/utils/yaml/loader.cpython-313-aarch64-linux-gnu.so
pyats/utils/yaml/markup.cpython-313-aarch64-linux-gnu.so
pyats/utils/yaml/utils.cpython-313-aarch64-linux-gnu.so
pyats_utils-25.9.dist-info/METADATA
pyats_utils-25.9.dist-info/WHEEL
pyats_utils-25.9.dist-info/entry_points.txt
pyats_utils-25.9.dist-info/top_level.txt
pyats_utils-25.9.dist-info/RECORD
